{
  "item": {
    "id": "f28f65ca1331",
    "url": "https://www.instagram.com/reel/DCG3VECy-W5/?igsh=bDZpdno2eDRnaTJ6",
    "source": "Instagram",
    "captured_at": "2026-04-19T16:08:31Z",
    "title": "Instagram",
    "summary_3lines": "",
    "tags": [],
    "category": "",
    "confidence": 0.0,
    "tried": false,
    "tried_at": null,
    "author": "",
    "body": "Instagram\nLog In\nSign Up",
    "key_takeaways": [],
    "why_it_matters": "",
    "what_to_try": "",
    "body_ko": "",
    "original_language": ""
  },
  "extracted": {
    "title": "Instagram",
    "text": "Instagram\nLog In\nSign Up",
    "html_len": 933161
  }
}